redback_jax/__init__.py
redback_jax/inference/__init__.py
redback_jax/models/__init__.py
redback_jax/utils/__init__.py
redback_jax-0.1.0.dist-info/licenses/LICENSE
redback_jax-0.1.0.dist-info/METADATA
redback_jax-0.1.0.dist-info/WHEEL
redback_jax-0.1.0.dist-info/top_level.txt
redback_jax-0.1.0.dist-info/RECORD
