Metadata-Version: 2.4
Name: redback-jax
Version: 0.1.0
Summary: A lightweight JAX-only version of redback for electromagnetic transient analysis
Author-email: Nikhil Sarin <nsarin.astro@gmail.com>
Maintainer-email: Nikhil Sarin <nsarin.astro@gmail.com>
License: GPL-3.0
Project-URL: Homepage, https://github.com/nikhil-sarin/redback-jax
Project-URL: Repository, https://github.com/nikhil-sarin/redback-jax
Project-URL: Documentation, https://redback-jax.readthedocs.io
Project-URL: Bug Tracker, https://github.com/nikhil-sarin/redback-jax/issues
Keywords: astronomy,astrophysics,transients,bayesian,jax
Classifier: Development Status :: 3 - Alpha
Classifier: Intended Audience :: Science/Research
Classifier: License :: OSI Approved :: GNU General Public License v3 (GPLv3)
Classifier: Operating System :: OS Independent
Classifier: Programming Language :: Python :: 3
Classifier: Programming Language :: Python :: 3.8
Classifier: Programming Language :: Python :: 3.9
Classifier: Programming Language :: Python :: 3.10
Classifier: Programming Language :: Python :: 3.11
Classifier: Programming Language :: Python :: 3.12
Classifier: Topic :: Scientific/Engineering :: Astronomy
Classifier: Topic :: Scientific/Engineering :: Physics
Requires-Python: >=3.8
License-File: LICENSE
Requires-Dist: jax>=0.4.0
Requires-Dist: jaxlib>=0.4.0
Requires-Dist: numpy>=1.20.0
Requires-Dist: scipy>=1.7.0
Requires-Dist: pandas>=1.3.0
Requires-Dist: matplotlib>=3.5.0
Requires-Dist: astropy>=4.0.0
Provides-Extra: all
Requires-Dist: numpyro>=0.12.0; extra == "all"
Requires-Dist: blackjax>=1.0.0; extra == "all"
Requires-Dist: optax>=0.1.0; extra == "all"
Provides-Extra: dev
Requires-Dist: pytest>=6.0; extra == "dev"
Requires-Dist: pytest-cov; extra == "dev"
Requires-Dist: black; extra == "dev"
Requires-Dist: isort; extra == "dev"
Requires-Dist: flake8; extra == "dev"
Requires-Dist: pre-commit; extra == "dev"
Dynamic: license-file
